{"display":{"gui":{"rotation":[-150.0,-45.0,180.0]}},"elements":[{"faces":{"down":{"rotation":270,"texture":"#0","tintindex":0,"uv":[3.0,3.5,4.0,4.5]},"east":{"rotation":0,"texture":"#0","tintindex":0,"uv":[3.5,0.0,4.5,1.0]},"north":{"rotation":0,"texture":"#0","tintindex":0,"uv":[4.5,0.0,3.5,1.0]},"south":{"rotation":0,"texture":"#0","tintindex":0,"uv":[4.5,0.0,3.5,1.0]},"up":{"rotation":90,"texture":"#0","tintindex":0,"uv":[2.0,3.5,3.0,4.5]},"west":{"rotation":0,"texture":"#0","tintindex":0,"uv":[3.5,0.0,4.5,1.0]}},"from":[16.874771,2.25,0.6442003],"rotation":{"angle":22.5,"axis":"y","origin":[17.374771,2.75,1.1442003]},"to":[17.874771,3.25,1.6442003]},{"faces":{"down":{"rotation":270,"texture":"#0","tintindex":0,"uv":[4.0,3.5,3.0,4.5]},"east":{"rotation":0,"texture":"#0","tintindex":0,"uv":[4.5,0.0,3.5,1.0]},"north":{"rotation":0,"texture":"#0","tintindex":0,"uv":[3.5,0.0,4.5,1.0]},"south":{"rotation":0,"texture":"#0","tintindex":0,"uv":[3.5,0.0,4.5,1.0]},"up":{"rotation":90,"texture":"#0","tintindex":0,"uv":[3.0,3.5,2.0,4.5]},"west":{"rotation":0,"texture":"#0","tintindex":0,"uv":[4.5,0.0,3.5,1.0]}},"from":[16.749771,2.5,-2.3571901],"rotation":{"angle":-45.0,"axis":"z","origin":[17.249771,3.0,-1.8571901]},"to":[17.749771,3.5,-1.3571901]},{"faces":{"down":{"rotation":0,"texture":"#0","tintindex":0,"uv":[3.0,3.5,4.0,4.5]},"east":{"rotation":0,"texture":"#0","tintindex":0,"uv":[4.5,0.0,3.5,1.0]},"north":{"rotation":0,"texture":"#0","tintindex":0,"uv":[3.5,0.0,4.5,1.0]},"south":{"rotation":0,"texture":"#0","tintindex":0,"uv":[3.5,0.0,4.5,1.0]},"up":{"rotation":0,"texture":"#0","tintindex":0,"uv":[2.0,3.5,3.0,4.5]},"west":{"rotation":0,"texture":"#0","tintindex":0,"uv":[4.5,0.0,3.5,1.0]}},"from":[6.000695,2.25,-14.231266],"rotation":{"angle":22.5,"axis":"y","origin":[6.500695,2.75,-13.731266]},"to":[7.000695,3.25,-13.231266]},{"faces":{"down":{"rotation":0,"texture":"#0","tintindex":0,"uv":[4.0,4.5,3.0,3.5]},"east":{"rotation":0,"texture":"#0","tintindex":0,"uv":[4.5,0.0,3.5,1.0]},"north":{"rotation":0,"texture":"#0","tintindex":0,"uv":[3.5,0.0,4.5,1.0]},"south":{"rotation":0,"texture":"#0","tintindex":0,"uv":[3.5,0.0,4.5,1.0]},"up":{"rotation":0,"texture":"#0","tintindex":0,"uv":[3.0,4.5,2.0,3.5]},"west":{"rotation":0,"texture":"#0","tintindex":0,"uv":[4.5,0.0,3.5,1.0]}},"from":[1.9993048,2.25,11.518275],"rotation":{"angle":22.5,"axis":"y","origin":[2.4993048,2.75,12.018275]},"to":[2.9993048,3.25,12.518275]},{"faces":{"down":{"rotation":0,"texture":"#0","tintindex":0,"uv":[4.0,3.5,3.0,4.5]},"east":{"rotation":0,"texture":"#0","tintindex":0,"uv":[3.5,0.0,4.5,1.0]},"north":{"rotation":0,"texture":"#0","tintindex":0,"uv":[4.5,0.0,3.5,1.0]},"south":{"rotation":0,"texture":"#0","tintindex":0,"uv":[4.5,0.0,3.5,1.0]},"up":{"rotation":0,"texture":"#0","tintindex":0,"uv":[3.0,3.5,2.0,4.5]},"west":{"rotation":0,"texture":"#0","tintindex":0,"uv":[3.5,0.0,4.5,1.0]}},"from":[8.999305,2.0,8.393735],"rotation":{"angle":-45.0,"axis":"z","origin":[9.499305,2.5,8.893735]},"to":[9.999305,3.0,9.393735]},{"faces":{"down":{"rotation":270,"texture":"#0","tintindex":0,"uv":[3.0,4.5,4.0,3.5]},"east":{"rotation":0,"texture":"#0","tintindex":0,"uv":[4.5,0.0,3.5,1.0]},"north":{"rotation":0,"texture":"#0","tintindex":0,"uv":[3.5,0.0,4.5,1.0]},"south":{"rotation":0,"texture":"#0","tintindex":0,"uv":[3.5,0.0,4.5,1.0]},"up":{"rotation":90,"texture":"#0","tintindex":0,"uv":[2.0,4.5,3.0,3.5]},"west":{"rotation":0,"texture":"#0","tintindex":0,"uv":[4.5,0.0,3.5,1.0]}},"from":[13.75023,2.0,-6.3557997],"rotation":{"angle":-45.0,"axis":"x","origin":[14.25023,2.5,-5.8557997]},"to":[14.75023,3.0,-5.3557997]},{"faces":{"down":{"rotation":0,"texture":"#0","tintindex":0,"uv":[3.0,4.5,4.0,3.5]},"east":{"rotation":0,"texture":"#0","tintindex":0,"uv":[4.5,0.0,3.5,1.0]},"north":{"rotation":0,"texture":"#0","tintindex":0,"uv":[3.5,0.0,4.5,1.0]},"south":{"rotation":0,"texture":"#0","tintindex":0,"uv":[3.5,0.0,4.5,1.0]},"up":{"rotation":0,"texture":"#0","tintindex":0,"uv":[2.0,3.5,3.0,4.5]},"west":{"rotation":0,"texture":"#0","tintindex":0,"uv":[4.5,0.0,3.5,1.0]}},"from":[8.499305,2.5,-10.106724],"rotation":{"angle":-45.0,"axis":"z","origin":[8.999305,3.0,-9.606724]},"to":[9.499305,3.5,-9.106724]},{"faces":{"down":{"rotation":270,"texture":"#0","tintindex":0,"uv":[3.0,4.5,4.0,3.5]},"east":{"rotation":0,"texture":"#0","tintindex":0,"uv":[4.5,0.0,3.5,1.0]},"north":{"rotation":0,"texture":"#0","tintindex":0,"uv":[3.5,0.0,4.5,1.0]},"south":{"rotation":0,"texture":"#0","tintindex":0,"uv":[3.5,0.0,4.5,1.0]},"up":{"rotation":90,"texture":"#0","tintindex":0,"uv":[2.0,4.5,3.0,3.5]},"west":{"rotation":0,"texture":"#0","tintindex":0,"uv":[4.5,0.0,3.5,1.0]}},"from":[-8.749771,2.5,-0.35579967],"rotation":{"angle":45.0,"axis":"z","origin":[-8.249771,3.0,0.14420033]},"to":[-7.74977,3.5,0.6442003]},{"faces":{"down":{"rotation":0,"texture":"#0","tintindex":0,"uv":[3.0,4.5,4.0,3.5]},"east":{"rotation":0,"texture":"#0","tintindex":0,"uv":[3.5,0.0,4.5,1.0]},"north":{"rotation":0,"texture":"#0","tintindex":0,"uv":[4.5,0.0,3.5,1.0]},"south":{"rotation":0,"texture":"#0","tintindex":0,"uv":[4.5,0.0,3.5,1.0]},"up":{"rotation":0,"texture":"#0","tintindex":0,"uv":[2.0,4.5,3.0,3.5]},"west":{"rotation":0,"texture":"#0","tintindex":0,"uv":[3.5,0.0,4.5,1.0]}},"from":[-0.9993048,2.0,-11.106724],"rotation":{"angle":45.0,"axis":"z","origin":[-0.49930477,2.5,-10.606724]},"to":[0.0006952286,3.0,-10.106724]},{"faces":{"down":{"rotation":0,"texture":"#0","tintindex":0,"uv":[4.0,3.5,3.0,4.5]},"east":{"rotation":0,"texture":"#0","tintindex":0,"uv":[4.5,0.0,3.5,1.0]},"north":{"rotation":0,"texture":"#0","tintindex":0,"uv":[3.5,0.0,4.5,1.0]},"south":{"rotation":0,"texture":"#0","tintindex":0,"uv":[3.5,0.0,4.5,1.0]},"up":{"rotation":0,"texture":"#0","tintindex":0,"uv":[3.0,4.5,2.0,3.5]},"west":{"rotation":0,"texture":"#0","tintindex":0,"uv":[4.5,0.0,3.5,1.0]}},"from":[-0.49930477,2.5,7.393735],"rotation":{"angle":45.0,"axis":"z","origin":[0.0006952286,3.0,7.893735]},"to":[0.5006952,3.5,8.393735]},{"faces":{"down":{"rotation":0,"texture":"#0","tintindex":0,"uv":[4.0,3.5,3.0,4.5]},"east":{"rotation":0,"texture":"#0","tintindex":0,"uv":[3.5,0.0,4.5,1.0]},"north":{"rotation":0,"texture":"#0","tintindex":0,"uv":[4.5,0.0,3.5,1.0]},"south":{"rotation":0,"texture":"#0","tintindex":0,"uv":[4.5,0.0,3.5,1.0]},"up":{"rotation":0,"texture":"#0","tintindex":0,"uv":[3.0,3.5,2.0,4.5]},"west":{"rotation":0,"texture":"#0","tintindex":0,"uv":[3.5,0.0,4.5,1.0]}},"from":[2.9993048,2.5,-14.106266],"rotation":{"angle":-45.0,"axis":"x","origin":[3.4993048,3.0,-13.606266]},"to":[3.9993048,3.5,-13.106266]},{"faces":{"down":{"rotation":270,"texture":"#0","tintindex":0,"uv":[3.0,4.5,4.0,3.5]},"east":{"rotation":0,"texture":"#0","tintindex":0,"uv":[3.5,0.0,4.5,1.0]},"north":{"rotation":0,"texture":"#0","tintindex":0,"uv":[4.5,0.0,3.5,1.0]},"south":{"rotation":0,"texture":"#0","tintindex":0,"uv":[4.5,0.0,3.5,1.0]},"up":{"rotation":90,"texture":"#0","tintindex":0,"uv":[2.0,3.5,3.0,4.5]},"west":{"rotation":0,"texture":"#0","tintindex":0,"uv":[3.5,0.0,4.5,1.0]}},"from":[12.75023,2.5,3.1428099],"rotation":{"angle":45.0,"axis":"x","origin":[13.25023,3.0,3.6428099]},"to":[13.75023,3.5,4.14281]},{"faces":{"down":{"rotation":270,"texture":"#0","tintindex":0,"uv":[4.0,3.5,3.0,4.5]},"east":{"rotation":0,"texture":"#0","tintindex":0,"uv":[4.5,0.0,3.5,1.0]},"north":{"rotation":0,"texture":"#0","tintindex":0,"uv":[3.5,0.0,4.5,1.0]},"south":{"rotation":0,"texture":"#0","tintindex":0,"uv":[3.5,0.0,4.5,1.0]},"up":{"rotation":90,"texture":"#0","tintindex":0,"uv":[3.0,3.5,2.0,4.5]},"west":{"rotation":0,"texture":"#0","tintindex":0,"uv":[4.5,0.0,3.5,1.0]}},"from":[-5.75023,2.0,3.6428099],"rotation":{"angle":45.0,"axis":"x","origin":[-5.25023,2.5,4.14281]},"to":[-4.75023,3.0,4.64281]},{"faces":{"down":{"rotation":270,"texture":"#0","tintindex":0,"uv":[4.0,3.5,3.0,4.5]},"east":{"rotation":0,"texture":"#0","tintindex":0,"uv":[3.5,0.0,4.5,1.0]},"north":{"rotation":0,"texture":"#0","tintindex":0,"uv":[4.5,0.0,3.5,1.0]},"south":{"rotation":0,"texture":"#0","tintindex":0,"uv":[4.5,0.0,3.5,1.0]},"up":{"rotation":90,"texture":"#0","tintindex":0,"uv":[3.0,4.5,2.0,3.5]},"west":{"rotation":0,"texture":"#0","tintindex":0,"uv":[3.5,0.0,4.5,1.0]}},"from":[-4.75023,2.5,-5.8557997],"rotation":{"angle":-45.0,"axis":"x","origin":[-4.25023,3.0,-5.3557997]},"to":[-3.7502298,3.5,-4.8557997]},{"faces":{"down":{"rotation":270,"texture":"#0","tintindex":0,"uv":[4.0,4.5,3.0,3.5]},"east":{"rotation":0,"texture":"#0","tintindex":0,"uv":[3.5,0.0,4.5,1.0]},"north":{"rotation":0,"texture":"#0","tintindex":0,"uv":[4.5,0.0,3.5,1.0]},"south":{"rotation":0,"texture":"#0","tintindex":0,"uv":[4.5,0.0,3.5,1.0]},"up":{"rotation":90,"texture":"#0","tintindex":0,"uv":[3.0,4.5,2.0,3.5]},"west":{"rotation":0,"texture":"#0","tintindex":0,"uv":[3.5,0.0,4.5,1.0]}},"from":[-8.874771,2.25,-3.3571901],"rotation":{"angle":22.5,"axis":"y","origin":[-8.374771,2.75,-2.8571901]},"to":[-7.87477,3.25,-2.3571901]},{"faces":{"down":{"rotation":0,"texture":"#0","tintindex":0,"uv":[3.0,4.5,4.0,3.5]},"east":{"rotation":0,"texture":"#0","tintindex":0,"uv":[3.5,0.0,4.5,1.0]},"north":{"rotation":0,"texture":"#0","tintindex":0,"uv":[4.5,0.0,3.5,1.0]},"south":{"rotation":0,"texture":"#0","tintindex":0,"uv":[4.5,0.0,3.5,1.0]},"up":{"rotation":0,"texture":"#0","tintindex":0,"uv":[2.0,4.5,3.0,3.5]},"west":{"rotation":0,"texture":"#0","tintindex":0,"uv":[3.5,0.0,4.5,1.0]}},"from":[5.000695,2.5,11.393275],"rotation":{"angle":45.0,"axis":"x","origin":[5.500695,3.0,11.893275]},"to":[6.000695,3.5,12.393275]}],"textures":{"0":"modelengine:custom/rose_vine_pod_decoration","particle":"#0"}}